{
  "Giant Slayer Greatsword": {
    "Type": "Weapon",
    "Rarity": "Rare",
    "Power": "Major",
    "Attune?": "No",
    "Use": "Permanent",
    "Curse": "Cursed",
    "Source": "DMG",
    "Page": "DMG 142",
    "Mat. Base Price": 500,
    "No. of Mat.": 8,
    "Material Cost": 4000,
    "Labor Cost": 1000,
    "Total Cost": 5000,
    "Meine Kosten": 7500
  },
  "Giant Slayer Handaxe": {
    "Type": "Weapon",
    "Rarity": "Rare",
    "Power": "Major",
    "Attune?": "Yes",
    "Use": "Permanent",
    "Curse": null,
    "Source": "DMG",
    "Page": "DMG 172",
    "Mat. Base Price": 500,
    "No. of Mat.": 8,
    "Material Cost": 4000,
    "Labor Cost": 1000,
    "Total Cost": 5000,
    "Meine Kosten": 7500
  },
  "Giant Slayer Longsword": {
    "Type": "Weapon",
    "Rarity": "Rare",
    "Power": "Major",
    "Attune?": "No",
    "Use": "Permanent",
    "Curse": null,
    "Source": "DMG",
    "Page": "DMG 172",
    "Mat. Base Price": 500,
    "No. of Mat.": 8,
    "Material Cost": 4000,
    "Labor Cost": 1000,
    "Total Cost": 5000,
    "Meine Kosten": 7500
  },
  "Giant Slayer Rapier": {
    "Type": "Weapon",
    "Rarity": "Rare",
    "Power": "Major",
    "Attune?": "No",
    "Use": "Permanent",
    "Curse": null,
    "Source": "DMG",
    "Page": "DMG 172",
    "Mat. Base Price": 500,
    "No. of Mat.": 8,
    "Material Cost": 4000,
    "Labor Cost": 1000,
    "Total Cost": 5000,
    "Meine Kosten": 7500
  },
  "Giant Slayer Scimitar": {
    "Type": "Weapon",
    "Rarity": "Rare",
    "Power": "Major",
    "Attune?": "No",
    "Use": "Permanent",
    "Curse": null,
    "Source": "DMG",
    "Page": "DMG 172",
    "Mat. Base Price": 500,
    "No. of Mat.": 8,
    "Material Cost": 4000,
    "Labor Cost": 1000,
    "Total Cost": 5000,
    "Meine Kosten": 7500
  },
  "Giant Slayer Shortsword": {
    "Type": "Weapon",
    "Rarity": "Rare",
    "Power": "Major",
    "Attune?": "No",
    "Use": "Permanent",
    "Curse": null,
    "Source": "DMG",
    "Page": "DMG 172",
    "Mat. Base Price": 500,
    "No. of Mat.": 8,
    "Material Cost": 4000,
    "Labor Cost": 1000,
    "Total Cost": 5000,
    "Meine Kosten": 7500
  },
  "Glaive of Warning": {
    "Type": "Weapon",
    "Rarity": "Uncommon",
    "Power": "Major",
    "Attune?": "Yes",
    "Use": "Permanent",
    "Curse": null,
    "Source": "DMG",
    "Page": "DMG 213",
    "Mat. Base Price": 50,
    "No. of Mat.": 8,
    "Material Cost": 400,
    "Labor Cost": 100,
    "Total Cost": 500,
    "Meine Kosten": 1250
  },
  "Glamoured Studded Leather Armor": {
    "Type": "Armor",
    "Rarity": "Rare",
    "Power": "Major",
    "Attune?": "No",
    "Use": "Permanent",
    "Curse": null,
    "Source": "DMG",
    "Page": "DMG 172",
    "Mat. Base Price": 500,
    "No. of Mat.": 8,
    "Material Cost": 4000,
    "Labor Cost": 1000,
    "Total Cost": 5000,
    "Meine Kosten": 7500
  },
  "Gloves of Missile Snaring": {
    "Type": "Wondrous Item",
    "Rarity": "Uncommon",
    "Power": "Major",
    "Attune?": "Yes",
    "Use": "Permanent",
    "Curse": null,
    "Source": "DMG",
    "Page": "DMG 172",
    "Mat. Base Price": 50,
    "No. of Mat.": 8,
    "Material Cost": 400,
    "Labor Cost": 100,
    "Total Cost": 500,
    "Meine Kosten": 1250
  },
  "Gloves of Swimming and Climbing": {
    "Type": "Wondrous Item",
    "Rarity": "Uncommon",
    "Power": "Major",
    "Attune?": "Yes",
    "Use": "Permanent",
    "Curse": null,
    "Source": "DMG",
    "Page": "DMG 172",
    "Mat. Base Price": 50,
    "No. of Mat.": 8,
    "Material Cost": 400,
    "Labor Cost": 100,
    "Total Cost": 500,
    "Meine Kosten": 1250
  },
"+1 Arrows": {
    "Type": "Weapon",
    "Rarity": "Uncommon",
    "Power": "Minor",
    "Attune?": "No",
    "Use": "Limited",
    "Curse": null,
    "Source": "DMG",
    "Page": "DMG 150",
    "Mat. Base Price": "5s0",
    "No. of Mat.": 4,
    "Material Cost": 200,
    "Labor Cost": 100,
    "Total Cost": 300,
    "Meine Kosten": 750
  }
}